zcommon4py/__init__.py
zcommon4py/logger.py
zcommon4py/threader.py
zcommon4py/timer.py
zcommon4py-1.0.2.dist-info/LICENSE.txt
zcommon4py-1.0.2.dist-info/METADATA
zcommon4py-1.0.2.dist-info/WHEEL
zcommon4py-1.0.2.dist-info/entry_points.txt
zcommon4py-1.0.2.dist-info/top_level.txt
zcommon4py-1.0.2.dist-info/RECORD
