Metadata-Version: 2.1
Name: zcommon4py
Version: 1.0.2
Summary: Modern utils library
Home-page: https://github.com/mazino2d/zcommon4py
Author: Khoi Dang Do
Author-email: mazino2d@gmail.com
License: MIT
Keywords: utils
Platform: UNKNOWN
Requires-Python: >=3.5, <4
